snirocr/Tesseract-OCR.zip
snirocr/__init__.py
snirocr/first_click.wav
snirocr/negativebeep.wav
snirocr/second_click.wav
snirocr/startup.wav
snirocr/success.wav
snirocr-0.1.6.dist-info/METADATA
snirocr-0.1.6.dist-info/WHEEL
snirocr-0.1.6.dist-info/top_level.txt
snirocr-0.1.6.dist-info/RECORD
